seamm_installer/__init__.py
seamm_installer/__main__.py
seamm_installer/_version.py
seamm_installer/apps.py
seamm_installer/cache.py
seamm_installer/cli.py
seamm_installer/conda.py
seamm_installer/configuration.py
seamm_installer/datastore.py
seamm_installer/gui.py
seamm_installer/install.py
seamm_installer/installer_base.py
seamm_installer/linux.py
seamm_installer/mac.py
seamm_installer/metadata.py
seamm_installer/my.py
seamm_installer/pip.py
seamm_installer/services.py
seamm_installer/show.py
seamm_installer/uninstall.py
seamm_installer/update.py
seamm_installer/util.py
seamm_installer/data/SEAMM.icns
seamm_installer/data/development.yml
seamm_installer/data/seamm.ini
seamm_installer/data/seamm.yml
seamm_installer/data/linux_icons/128x128.png
seamm_installer/data/linux_icons/16x16.png
seamm_installer/data/linux_icons/24x24.png
seamm_installer/data/linux_icons/256x256.png
seamm_installer/data/linux_icons/32x32.png
seamm_installer/data/linux_icons/48x48.png
seamm_installer/data/linux_icons/512x512.png
seamm_installer/data/linux_icons/64x64.png
seamm_installer-2025.8.22.dist-info/licenses/AUTHORS.rst
seamm_installer-2025.8.22.dist-info/licenses/LICENSE
seamm_installer-2025.8.22.dist-info/METADATA
seamm_installer-2025.8.22.dist-info/WHEEL
seamm_installer-2025.8.22.dist-info/entry_points.txt
seamm_installer-2025.8.22.dist-info/top_level.txt
seamm_installer-2025.8.22.dist-info/zip-safe
seamm_installer-2025.8.22.dist-info/RECORD
