Metadata-Version: 2.4
Name: seamm-installer
Version: 2025.8.22
Summary: The installer/updater for SEAMM (Simulation Environment for Atomistic and Molecular Simulations).
Home-page: https://github.com/molssi-seamm/seamm_installer
Author: Paul Saxe
Author-email: psaxe@molssi.org
License: GNU Lesser General Public License v3+
Keywords: SEAMM,plug-in,flowchart,installer,updater
Platform: Linux
Platform: Mac OS-X
Platform: Unix
Platform: Windows
Classifier: Development Status :: 5 - Production/Stable
Classifier: Intended Audience :: Science/Research
Classifier: Topic :: Scientific/Engineering :: Chemistry
Classifier: Topic :: Scientific/Engineering :: Physics
Classifier: License :: OSI Approved :: GNU Lesser General Public License v3 or later (LGPLv3+)
Classifier: Natural Language :: English
Classifier: Programming Language :: Python :: 3 :: Only
Classifier: Programming Language :: Python :: 3.8
Classifier: Programming Language :: Python :: 3.9
License-File: LICENSE
License-File: AUTHORS.rst
Requires-Dist: alembic
Requires-Dist: packaging
Requires-Dist: platformdirs
Requires-Dist: pmw
Requires-Dist: requests
Requires-Dist: seamm-widgets
Requires-Dist: tabulate
Dynamic: author
Dynamic: author-email
Dynamic: classifier
Dynamic: description
Dynamic: description-content-type
Dynamic: home-page
Dynamic: keywords
Dynamic: license
Dynamic: license-file
Dynamic: platform
Dynamic: requires-dist
Dynamic: summary
